yretry/__init__.py
yretry/decorators.py
yretry/defaults.py
yretry/network.py
yretry/tests/__init__.py
yretry/tests/base.py
yretry/tests/test_decorators.py
yretry/tests/test_network.py
yretry-1.0.1.dist-info/licenses/AUTHORS
yretry-1.0.1.dist-info/licenses/LICENSE
yretry-1.0.1.dist-info/METADATA
yretry-1.0.1.dist-info/WHEEL
yretry-1.0.1.dist-info/pbr.json
yretry-1.0.1.dist-info/top_level.txt
yretry-1.0.1.dist-info/RECORD
