Metadata-Version: 2.4
Name: yretry
Version: 1.0.1
Summary: Retries library
Home-page: https://github.com/infraguys/yretry
Author: InfraGuys
Classifier: License :: OSI Approved :: Apache Software License
Classifier: Operating System :: POSIX :: Linux
Classifier: Programming Language :: Python
Classifier: Programming Language :: Python :: 2
Classifier: Programming Language :: Python :: 2.7
Classifier: Programming Language :: Python :: 3
Classifier: Programming Language :: Python :: 3.6
Classifier: Programming Language :: Python :: 3.8
Classifier: Programming Language :: Python :: 3.10
Classifier: Programming Language :: Python :: 3.12
License-File: LICENSE
License-File: AUTHORS
Requires-Dist: pbr<=5.8.1,>=1.10.0
Requires-Dist: requests<3.0.0,>=2.32.4
Requires-Dist: six<=1.16.0,>=1.13.0
Dynamic: author
Dynamic: classifier
Dynamic: description
Dynamic: home-page
Dynamic: license-file
Dynamic: requires-dist
Dynamic: summary
